{
	"$schema": "http://schema.management.azure.com/schemas/2015-01-01/deploymentTemplate.json#",
	"contentVersion": "1.0.0.0",
	"parameters": {
		"factoryName": {
			"type": "string",
			"metadata": "Data Factory name",
			"defaultValue": "aruntomar0810-df"
		},
		"AzureBlobStorage1_connectionString": {
			"type": "secureString",
			"metadata": "Secure string for 'connectionString' of 'AzureBlobStorage1'"
		},
		"AzureSqlDatabase1_connectionString": {
			"type": "secureString",
			"metadata": "Secure string for 'connectionString' of 'AzureSqlDatabase1'"
		}
	},
	"variables": {
		"factoryId": "[concat('Microsoft.DataFactory/factories/', parameters('factoryName'))]"
	},
	"resources": [
		{
			"name": "[concat(parameters('factoryName'), '/AzureBlobStorage1')]",
			"type": "Microsoft.DataFactory/factories/linkedServices",
			"apiVersion": "2018-06-01",
			"properties": {
				"annotations": [],
				"type": "AzureBlobStorage",
				"typeProperties": {
					"connectionString": "[parameters('AzureBlobStorage1_connectionString')]"
				}
			},
			"dependsOn": []
		},
		{
			"name": "[concat(parameters('factoryName'), '/AzureSqlDatabase1')]",
			"type": "Microsoft.DataFactory/factories/linkedServices",
			"apiVersion": "2018-06-01",
			"properties": {
				"annotations": [],
				"type": "AzureSqlDatabase",
				"typeProperties": {
					"connectionString": "[parameters('AzureSqlDatabase1_connectionString')]"
				}
			},
			"dependsOn": []
		},
		{
			"name": "[concat(parameters('factoryName'), '/AzureSqlTable1')]",
			"type": "Microsoft.DataFactory/factories/datasets",
			"apiVersion": "2018-06-01",
			"properties": {
				"linkedServiceName": {
					"referenceName": "AzureSqlDatabase1",
					"type": "LinkedServiceReference"
				},
				"annotations": [],
				"type": "AzureSqlTable",
				"schema": [
					{
						"name": "EMPLOYEE_ID",
						"type": "float",
						"precision": 15
					},
					{
						"name": "FIRST_NAME",
						"type": "varchar"
					},
					{
						"name": "LAST_NAME",
						"type": "varchar"
					},
					{
						"name": "EMAIL",
						"type": "varchar"
					},
					{
						"name": "PHONE_NUMBER",
						"type": "varchar"
					},
					{
						"name": "HIRE_DATE",
						"type": "datetime",
						"precision": 23,
						"scale": 3
					},
					{
						"name": "JOB_ID",
						"type": "varchar"
					},
					{
						"name": "SALARY",
						"type": "decimal",
						"precision": 8,
						"scale": 2
					},
					{
						"name": "COMMISSION_PCT",
						"type": "decimal",
						"precision": 2,
						"scale": 2
					},
					{
						"name": "MANAGER_ID",
						"type": "float",
						"precision": 15
					},
					{
						"name": "DEPARTMENT_ID",
						"type": "float",
						"precision": 15
					}
				],
				"typeProperties": {
					"schema": "dbo",
					"table": "EMPKOYEESD"
				}
			},
			"dependsOn": [
				"[concat(variables('factoryId'), '/linkedServices/AzureSqlDatabase1')]"
			]
		},
		{
			"name": "[concat(parameters('factoryName'), '/DelimitedText1')]",
			"type": "Microsoft.DataFactory/factories/datasets",
			"apiVersion": "2018-06-01",
			"properties": {
				"linkedServiceName": {
					"referenceName": "AzureBlobStorage1",
					"type": "LinkedServiceReference"
				},
				"annotations": [],
				"type": "DelimitedText",
				"typeProperties": {
					"location": {
						"type": "AzureBlobStorageLocation",
						"fileName": "dboEMPLOYEES.txt",
						"container": "adfdemo"
					},
					"columnDelimiter": ",",
					"escapeChar": "\\",
					"quoteChar": "\""
				},
				"schema": [
					{
						"type": "String"
					},
					{
						"type": "String"
					},
					{
						"type": "String"
					},
					{
						"type": "String"
					},
					{
						"type": "String"
					},
					{
						"type": "String"
					},
					{
						"type": "String"
					},
					{
						"type": "String"
					},
					{
						"type": "String"
					},
					{
						"type": "String"
					},
					{
						"type": "String"
					}
				]
			},
			"dependsOn": [
				"[concat(variables('factoryId'), '/linkedServices/AzureBlobStorage1')]"
			]
		},
		{
			"name": "[concat(parameters('factoryName'), '/DestinationDataset_sj5')]",
			"type": "Microsoft.DataFactory/factories/datasets",
			"apiVersion": "2018-06-01",
			"properties": {
				"linkedServiceName": {
					"referenceName": "AzureBlobStorage1",
					"type": "LinkedServiceReference"
				},
				"annotations": [],
				"type": "DelimitedText",
				"typeProperties": {
					"location": {
						"type": "AzureBlobStorageLocation",
						"fileName": "DIM",
						"folderPath": "output",
						"container": "adfdemo"
					},
					"columnDelimiter": ",",
					"escapeChar": "\\",
					"quoteChar": "\""
				},
				"schema": []
			},
			"dependsOn": [
				"[concat(variables('factoryId'), '/linkedServices/AzureBlobStorage1')]"
			]
		},
		{
			"name": "[concat(parameters('factoryName'), '/SourceDataset_sj5')]",
			"type": "Microsoft.DataFactory/factories/datasets",
			"apiVersion": "2018-06-01",
			"properties": {
				"linkedServiceName": {
					"referenceName": "AzureBlobStorage1",
					"type": "LinkedServiceReference"
				},
				"annotations": [],
				"type": "DelimitedText",
				"typeProperties": {
					"location": {
						"type": "AzureBlobStorageLocation",
						"container": "adfdemo"
					},
					"columnDelimiter": ",",
					"escapeChar": "\\",
					"firstRowAsHeader": true,
					"quoteChar": "\""
				},
				"schema": [
					{
						"name": "EMPLOYEE_ID",
						"type": "String"
					},
					{
						"name": "FIRST_NAME",
						"type": "String"
					},
					{
						"name": "LAST_NAME",
						"type": "String"
					},
					{
						"name": "EMAIL",
						"type": "String"
					},
					{
						"name": "PHONE_NUMBER",
						"type": "String"
					},
					{
						"name": "HIRE_DATE",
						"type": "String"
					},
					{
						"name": "JOB_ID",
						"type": "String"
					},
					{
						"name": "SALARY",
						"type": "String"
					},
					{
						"name": "COMMISSION_PCT",
						"type": "String"
					},
					{
						"name": "MANAGER_ID",
						"type": "String"
					},
					{
						"name": "DEPARTMENT_ID",
						"type": "String"
					}
				]
			},
			"dependsOn": [
				"[concat(variables('factoryId'), '/linkedServices/AzureBlobStorage1')]"
			]
		},
		{
			"name": "[concat(parameters('factoryName'), '/CopyPipeline_sj5')]",
			"type": "Microsoft.DataFactory/factories/pipelines",
			"apiVersion": "2018-06-01",
			"properties": {
				"activities": [
					{
						"name": "Copy_sj5",
						"type": "Copy",
						"dependsOn": [],
						"policy": {
							"timeout": "0.12:00:00",
							"retry": 0,
							"retryIntervalInSeconds": 30,
							"secureOutput": false,
							"secureInput": false
						},
						"userProperties": [
							{
								"name": "Source",
								"value": "adfdemo/"
							},
							{
								"name": "Destination",
								"value": "adfdemo/output/"
							}
						],
						"typeProperties": {
							"source": {
								"type": "DelimitedTextSource",
								"storeSettings": {
									"type": "AzureBlobStorageReadSettings",
									"recursive": true,
									"wildcardFileName": "*",
									"enablePartitionDiscovery": false
								},
								"formatSettings": {
									"type": "DelimitedTextReadSettings",
									"skipLineCount": 0
								}
							},
							"sink": {
								"type": "DelimitedTextSink",
								"storeSettings": {
									"type": "AzureBlobStorageWriteSettings",
									"copyBehavior": "MergeFiles"
								},
								"formatSettings": {
									"type": "DelimitedTextWriteSettings",
									"quoteAllText": true,
									"fileExtension": ".txt"
								}
							},
							"enableStaging": false,
							"validateDataConsistency": false,
							"translator": {
								"type": "TabularTranslator",
								"typeConversion": true,
								"typeConversionSettings": {
									"allowDataTruncation": true,
									"treatBooleanAsNumber": false
								}
							}
						},
						"inputs": [
							{
								"referenceName": "SourceDataset_sj5",
								"type": "DatasetReference",
								"parameters": {}
							}
						],
						"outputs": [
							{
								"referenceName": "DestinationDataset_sj5",
								"type": "DatasetReference",
								"parameters": {}
							}
						]
					}
				],
				"policy": {
					"elapsedTimeMetric": {},
					"cancelAfter": {}
				},
				"annotations": [],
				"lastPublishTime": "2023-04-30T20:04:55Z"
			},
			"dependsOn": [
				"[concat(variables('factoryId'), '/datasets/SourceDataset_sj5')]",
				"[concat(variables('factoryId'), '/datasets/DestinationDataset_sj5')]"
			]
		},
		{
			"name": "[concat(parameters('factoryName'), '/pipeline1')]",
			"type": "Microsoft.DataFactory/factories/pipelines",
			"apiVersion": "2018-06-01",
			"properties": {
				"activities": [
					{
						"name": "Copy data1",
						"type": "Copy",
						"dependsOn": [],
						"policy": {
							"timeout": "0.12:00:00",
							"retry": 0,
							"retryIntervalInSeconds": 30,
							"secureOutput": false,
							"secureInput": false
						},
						"userProperties": [],
						"typeProperties": {
							"source": {
								"type": "DelimitedTextSource",
								"storeSettings": {
									"type": "AzureBlobStorageReadSettings",
									"recursive": true,
									"enablePartitionDiscovery": false
								},
								"formatSettings": {
									"type": "DelimitedTextReadSettings",
									"skipLineCount": 1
								}
							},
							"sink": {
								"type": "AzureSqlSink",
								"writeBehavior": "upsert",
								"upsertSettings": {
									"useTempDB": true,
									"keys": [
										"EMPLOYEE_ID"
									]
								},
								"sqlWriterUseTableLock": false,
								"disableMetricsCollection": false
							},
							"enableStaging": false,
							"translator": {
								"type": "TabularTranslator",
								"mappings": [
									{
										"source": {
											"type": "String",
											"ordinal": 1
										},
										"sink": {
											"name": "EMPLOYEE_ID",
											"type": "Double",
											"physicalType": "float"
										}
									},
									{
										"source": {
											"type": "String",
											"ordinal": 2
										},
										"sink": {
											"name": "FIRST_NAME",
											"type": "String",
											"physicalType": "varchar"
										}
									},
									{
										"source": {
											"type": "String",
											"ordinal": 3
										},
										"sink": {
											"name": "LAST_NAME",
											"type": "String",
											"physicalType": "varchar"
										}
									},
									{
										"source": {
											"type": "String",
											"ordinal": 4
										},
										"sink": {
											"name": "EMAIL",
											"type": "String",
											"physicalType": "varchar"
										}
									},
									{
										"source": {
											"type": "String",
											"ordinal": 5
										},
										"sink": {
											"name": "PHONE_NUMBER",
											"type": "String",
											"physicalType": "varchar"
										}
									},
									{
										"source": {
											"type": "String",
											"ordinal": 6
										},
										"sink": {
											"name": "HIRE_DATE",
											"type": "DateTime",
											"physicalType": "datetime"
										}
									},
									{
										"source": {
											"type": "String",
											"ordinal": 7
										},
										"sink": {
											"name": "JOB_ID",
											"type": "String",
											"physicalType": "varchar"
										}
									},
									{
										"source": {
											"type": "String",
											"ordinal": 8
										},
										"sink": {
											"name": "SALARY",
											"type": "Decimal",
											"physicalType": "decimal",
											"scale": 2,
											"precision": 8
										}
									},
									{
										"source": {
											"type": "String",
											"ordinal": 9
										},
										"sink": {
											"name": "COMMISSION_PCT",
											"type": "Decimal",
											"physicalType": "decimal",
											"scale": 2,
											"precision": 2
										}
									},
									{
										"source": {
											"type": "String",
											"ordinal": 10
										},
										"sink": {
											"name": "MANAGER_ID",
											"type": "Double",
											"physicalType": "float"
										}
									},
									{
										"source": {
											"type": "String",
											"ordinal": 11
										},
										"sink": {
											"name": "DEPARTMENT_ID",
											"type": "Double",
											"physicalType": "float"
										}
									}
								],
								"typeConversion": true,
								"typeConversionSettings": {
									"allowDataTruncation": true,
									"treatBooleanAsNumber": false
								}
							}
						},
						"inputs": [
							{
								"referenceName": "DelimitedText1",
								"type": "DatasetReference",
								"parameters": {}
							}
						],
						"outputs": [
							{
								"referenceName": "AzureSqlTable1",
								"type": "DatasetReference",
								"parameters": {}
							}
						]
					}
				],
				"policy": {
					"elapsedTimeMetric": {},
					"cancelAfter": {}
				},
				"folder": {
					"name": "DEV"
				},
				"annotations": []
			},
			"dependsOn": [
				"[concat(variables('factoryId'), '/datasets/DelimitedText1')]",
				"[concat(variables('factoryId'), '/datasets/AzureSqlTable1')]"
			]
		}
	]
}